{
    "title": "What is polyjet 3D printing? - Quora",
    "tags": [
        "3D Design and 3D Printing",
        "3D Printers",
        "3D Printing",
        "3D Technology",
        "Printers",
        "Printing",
        "Manufacturing"
    ],
    "response": [
        {
            "author_info": {
                "name": "Super Channel",
                "href": "/profile/Super-Channel-27"
            },
            "answer_text": "PolyJet is a powerful 3D printing technology that produces smooth, accurate parts, prototypes and tooling. With microscopic layer resolution and accuracy down to 0.014 mm, it can produce thin walls and complex geometries using the widest range of materials available with any technology. ",
            "date": "Answered January 30, 2020",
            "views": "46",
            "upvotes": "0"
        }
    ]
}