{
    "title": "How to remove soap from the soap water - Quora",
    "tags": [
        "Special Chemistry",
        "Bathtub Chemistry"
    ],
    "response": [
        {
            "author_info": {
                "name": "Narinder Singh",
                "href": "/profile/Narinder-Singh-11"
            },
            "answer_text": "Add calcium hydroxide and boil the solution. Let the solution cool down you \u2018ll see some precipitates. Filter out these precipitates, these precipitates would be calcium salt of fatty acid which were part of your soap. Now these filtered precipitates can be converted back to Soap, by addition of lye and evaporation of water. Above mentioned process needs optimization basis the scale of operation. ",
            "date": "Answered November 26, 2017",
            "views": "21",
            "upvotes": " View 1 Upvoter ",
            "upvoters": [
                {
                    "user_id": "Kenneth Armstrong",
                    "user_href": "/profile/Kenneth-Armstrong-9"
                }
            ]
        },
        {
            "author_info": {
                "name": "Jovi George",
                "href": "/profile/Jovi-George-1"
            },
            "answer_text": "Pour some acid to the soap water. The soap will hydrolyse to fatty acid which can be decanted and removed. The fillers in soap can be removed by filtration and when distilling the water, the salts will be left behind and you will get water as distillate. ",
            "date": "Answered September 9, 2017",
            "views": "1",
            "upvotes": " View 3 Upvoters ",
            "upvoters": [
                {
                    "user_id": "Jeanette Le Roux",
                    "user_href": "/profile/Jeanette-Le-Roux-3"
                },
                {
                    "user_id": "Ali Osman",
                    "user_href": "/profile/Ali-Osman-39"
                },
                {
                    "user_id": "Shivangi Srivastava",
                    "user_href": "/profile/Shivangi-Srivastava-49"
                }
            ]
        }
    ]
}